hebill_html_document/__init__.py
hebill_html_document/main.py
hebill_html_document/document/__init__.py
hebill_html_document/document/create.py
hebill_html_document/document/nodes.py
hebill_html_document/document/tags.py
hebill_html_document/nodes/__init__.py
hebill_html_document/nodes/code.py
hebill_html_document/nodes/comment.py
hebill_html_document/nodes/content.py
hebill_html_document/nodes/group.py
hebill_html_document/nodes/node.py
hebill_html_document/nodes/tag.py
hebill_html_document/tags/__init__.py
hebill_html_document/tags/a.py
hebill_html_document/tags/body.py
hebill_html_document/tags/div.py
hebill_html_document/tags/head.py
hebill_html_document/tags/html.py
hebill_html_document/tags/input_text.py
hebill_html_document/tags/link.py
hebill_html_document/tags/span.py
hebill_html_document/tags/title.py
hebill_html_document/test/__init__.py
hebill_html_document/test/main.py
hebill_html_document/test/test_flask.py
hebill_html_document/test/test_local.py
hebill_html_document-1.1.dist-info/LICENSE.rst
hebill_html_document-1.1.dist-info/METADATA
hebill_html_document-1.1.dist-info/WHEEL
hebill_html_document-1.1.dist-info/top_level.txt
hebill_html_document-1.1.dist-info/RECORD
