Metadata-Version: 2.1
Name: hebill_html_document
Version: 1.1
Summary: Python Html Document Generator
Home-page: https://py.hebill.net/hebill_html_document
Author: He Bill
Author-email: hebill@me.com
Requires-Python: >=3.9
License-File: LICENSE.rst
